pytorche/__init__.py
pytorche/other.py
pytorche-0.0.1.dist-info/LICENSE
pytorche-0.0.1.dist-info/METADATA
pytorche-0.0.1.dist-info/WHEEL
pytorche-0.0.1.dist-info/top_level.txt
pytorche-0.0.1.dist-info/RECORD
