Metadata-Version: 2.1
Name: pytorche
Version: 0.0.1
Summary: pytorche ia tkt
Author-email: poloi <poloi@realemail.com>
Classifier: Programming Language :: Python :: 3
Classifier: License :: OSI Approved :: MIT License
Classifier: Operating System :: OS Independent
Requires-Python: >=3.6
License-File: LICENSE
